{"data": [
    {
        "id": "1",
        "faculty": "คณะวิทยาศาสตร์",
        "logo": "https://topumin.com/images/skooldio/science.jpg",
        "department": "ฟิสิกส์ประยุกต์ (หลักสูตรสองภาษา) สาขาเอกฟิสิกส์",
        "university": "มหาวิทยาลัยเทคโนโลยีพระจอมเกล้าธนุบรี",
        "round": ["1"],
        "min_score": ""
    },
    {
        "id": "2",
        "faculty": "คณะวิทยาศาสตร์",
        "logo": "https://topumin.com/images/skooldio/science.jpg",
        "department": "ฟิสิกส์ประยุกต์ (หลักสูตรสองภาษา) สาขาเอกฟิสิกส์วัสดุและเทคโนโลยีนาโน",
        "university": "มหาวิทยาลัยเทคโนโลยีพระจอมเกล้าธนุบรี",
        "round": ["1"],
        "min_score": ""
    },
    {
        "id": "3",
        "faculty": "คณะวิทยาศาสตร์",
        "department": "สาขาวิชาเคมี",
        "logo": "https://topumin.com/images/skooldio/science.jpg",
        "university": "มหาวิทยาลัยเทคโนโลยีพระจอมเกล้าธนุบรี",
        "round": ["1", "2", "3"],
        "min_score": "12,750.00"
    },
    {
        "id": "4",
        "faculty": "คณะวิทยาศาสตร์",
        "department": "สาขาวิชาคณิตศาสตร์",
        "logo": "https://topumin.com/images/skooldio/science.jpg",
        "university": "มหาวิทยาลัยเทคโนโลยีพระจอมเกล้าธนุบรี",
        "round": ["1", "2", "3"],
        "min_score": "13,460.60"
    },
    {
        "id": "5",
        "faculty": "คณะวิทยาศาสตร์",
        "department": "สาขาวิชาสถิติ",
        "logo": "https://topumin.com/images/skooldio/science.jpg",
        "university": "มหาวิทยาลัยเทคโนโลยีพระจอมเกล้าธนุบรี",
        "round": ["1", "2", "3"],
        "min_score": "3,915.00"
    },
    {
        "id": "6",
        "faculty": "คณะวิทยาศาสตร์",
        "department": "สาขาวิชาวิทยาการคอมพิวเตอร์ประยุกต์",
        "logo": "https://topumin.com/images/skooldio/science.jpg",
        "university": "มหาวิทยาลัยเทคโนโลยีพระจอมเกล้าธนุบรี",
        "round": ["1", "2", "3"],
        "min_score": "15,578.00"
    },
    {
        "id": "7",
        "faculty": "คณะวิทยาศาสตร์",
        "department": "สาขาวิชาจุลชีววิทยา",
        "logo": "https://topumin.com/images/skooldio/science.jpg",
        "university": "มหาวิทยาลัยเทคโนโลยีพระจอมเกล้าธนุบรี",
        "round": ["1", "2", "3"],
        "min_score": "14,018.20"
    },
    {
        "id": "8",
        "faculty": "คณะวิทยาศาสตร์",
        "department": "สาขาวิชาวิทยาศาสตร์การอาหาร",
        "logo": "https://topumin.com/images/skooldio/science.jpg",
        "university": "มหาวิทยาลัยเทคโนโลยีพระจอมเกล้าธนุบรี",
        "round": ["1", "2", "3"],
        "min_score": "16,314.90"
    },
    {
        "id": "9",
        "faculty": "คณะวิทยาศาสตร์",
        "department": "สาขาวิชาฟิสิกส์ประยุกต์ (หลักสูตรสองภาษา)",
        "logo": "https://topumin.com/images/skooldio/science.jpg",
        "university": "มหาวิทยาลัยเทคโนโลยีพระจอมเกล้าธนุบรี",
        "round": ["2", "3"],
        "min_score": "8,824.00"
    }
]}